Workbook

Sheet Read Me
A1: PargoParcels — Enterprise Analytics Engineering Portfolio
A2: Synthetic SA last-mile logistics dataset | 11.06M rows generated (scales to 220M) | Postgres OLTP -> Snowflake -> dbt
A4: This workbook contains representative samples of every table plus a formula-driven KPI summary.
A7: Sheet | B7: Type | C7: Rows | D7: Description
A8: Parcels Sample | B8: fact | C8: 1,000 of 1,200,931 | D8: Parcel lifecycle w/ milestone timestamps; delivery & dwell hours are live formulas
A9: Tracking Events Sample | B9: fact | C9: 1,000 of 8,368,335 | D9: Scan-level event log (~7 events per parcel)
A10: Returns Sample | B10: fact | C10: 500 of 85,769 | D10: Returns w/ reason taxonomy
A11: Monthly Volumes | B11: aggregate | C11: 36 months | D11: Network volumes by month; totals are formulas
A12: Retailers | B12: dimension | C12: all 150 | D12: Clients incl. Bash, Woolworths, Clicks, Sportscene + tiers and rate cards
A13: Pickup Points Sample | B13: dimension | C13: 500 of 4,000 | D13: Pargo Point network across all 9 provinces
A14: Customers Sample | B14: dimension | C14: 500 of 400,000 | D14: Synthetic consumers (PII is fake)
A15: Couriers | B15: dimension | C15: all 500 | D15: Courier fleet w/ regions and vehicle types
A16: KPI Summary | B16: analysis | C16: — | D16: Formula-driven KPIs computed from the samples
A18: Data note: This Excel workbook uses representative samples for performance. Full dashboard/eBook figures can differ from workbook sample KPIs; ML metrics use held-out validation data and business impact values are modelled estimates.

Sheet KPI Summary
A1: Network KPIs — computed live from 'Parcels Sample' (1,000 parcels)
A3: KPI | B3: Value
A4: Parcels in sample | B4: =COUNTA('Parcels Sample'!A2:A871)
A5: Avg delivery hours (created → at point) | B5: =AVERAGE('Parcels Sample'!Q2:Q871)
A6: Avg delivery days | B6: =AVERAGE('Parcels Sample'!Q2:Q871)/24
A7: Avg dwell hours (at point → collected) | B7: =AVERAGE('Parcels Sample'!R2:R871)
A8: Delivery success rate | B8: =(COUNTIF('Parcels Sample'!K2:K871,"Collected")+COUNTIF('Parcels Sample'!K2:K871,"Damaged"))/COUNTA('Parcels Sample'!K2:K871)
A9: Returned-to-sender rate | B9: =COUNTIF('Parcels Sample'!K2:K871,"ExpiredRTS")/COUNTA('Parcels Sample'!K2:K871)
A10: 48h SLA achievement | B10: =COUNTIF('Parcels Sample'!Q2:Q871,"<=48")/COUNT('Parcels Sample'!Q2:Q871)
A11: Avg parcel value (ZAR) | B11: =AVERAGE('Parcels Sample'!N2:N871)
A12: Avg delivery cost (ZAR) | B12: =AVERAGE('Parcels Sample'!P2:P871)
A13: Total parcels, 36 months (full table) | B13: ='Monthly Volumes'!B38
A14: Network avg delivery hours (full table) | B14: ='Monthly Volumes'!C38
A16: Note: sample-based KPIs will differ slightly from full-table figures shown in the eBook.

Sheet Parcels Sample
A1: parcel_id | B1: waybill_number | C1: retailer_id | D1: pickup_point_id | E1: courier_id | F1: created_at | G1: dispatched_at | H1: arrived_at_point_at | I1: notified_at | J1: collected_at | K1: parcel_status | L1: service_type | M1: province | N1: parcel_value_zar | O1: parcel_weight_kg | P1: delivery_cost_zar | Q1: delivery_hours | R1: dwell_hours
A2: 2012 | B2: PGO10002012 | C2: 97 | D2: 2293 | E2: 420 | F2: 45110.223 | G2: 45110.507 | H2: 45111.141 | I2: 45111.176 | J2: 45112.73 | K2: Collected | L2: Standard | M2: Gauteng | N2: 604.66 | O2: 0.64 | P2: 47.32 | Q2: =IF(H2="","",(H2-F2)*24) | R2: =IF(J2="","",(J2-H2)*24)
A3: 13776 | B3: PGO10013776 | C3: 5 | D3: 2997 | E3: 446 | F3: 45110.362 | G3: 45110.395 | H3: 45111.138 | I3: 45111.142 | J3: 45116.357 | K3: Collected | L3: Standard | M3: Gauteng | N3: 339.62 | O3: 2.5 | P3: 57.42 | Q3: =IF(H3="","",(H3-F3)*24) | R3: =IF(J3="","",(J3-H3)*24)
A4: 18742 | B4: PGO10018742 | C4: 4 | D4: 1830 | E4: 108 | F4: 45110.963 | G4: 45111.46 | H4: 45112.606 | I4: 45112.648 | J4: 45113.967 | K4: Collected | L4: Standard | M4: North West | N4: 459.4 | O4: 1.2 | P4: 41.31 | Q4: =IF(H4="","",(H4-F4)*24) | R4: =IF(J4="","",(J4-H4)*24)
A5: 6856 | B5: PGO10006856 | C5: 68 | D5: 3651 | E5: 313 | F5: 45115.711 | G5: 45115.852 | H5: 45116.691 | I5: 45116.748 | J5: 45117.109 | K5: Collected | L5: Express | M5: Gauteng | N5: 244.26 | O5: 1.98 | P5: 60.35 | Q5: =IF(H5="","",(H5-F5)*24) | R5: =IF(J5="","",(J5-H5)*24)
A6: 14457 | B6: PGO10014457 | C6: 6 | D6: 3554 | E6: 383 | F6: 45116.915 | G6: 45117.211 | H6: 45118.015 | I6: 45118.039 | J6: 45118.393 | K6: Collected | L6: Standard | M6: Gauteng | N6: 129.32 | O6: 1.33 | P6: 41.15 | Q6: =IF(H6="","",(H6-F6)*24) | R6: =IF(J6="","",(J6-H6)*24)
A7: 22191 | B7: PGO10022191 | C7: 43 | D7: 1216 | E7: 155 | F7: 45118.316 | G7: 45118.545 | H7: 45119.568 | I7: 45119.621 | J7: 45121.486 | K7: Collected | L7: Standard | M7: Western Cape | N7: 62.69 | O7: 5.91 | P7: 73.95 | Q7: =IF(H7="","",(H7-F7)*24) | R7: =IF(J7="","",(J7-H7)*24)
A8: 1650 | B8: PGO10001650 | C8: 30 | D8: 3609 | E8: 147 | F8: 45120.951 | G8: 45121.422 | H8: 45122.543 | I8: 45122.581 | J8: 45123.078 | K8: Collected | L8: Standard | M8: Mpumalanga | N8: 170.54 | O8: 0.89 | P8: 69.13 | Q8: =IF(H8="","",(H8-F8)*24) | R8: =IF(J8="","",(J8-H8)*24)
A9: 9376 | B9: PGO10009376 | C9: 13 | D9: 2679 | E9: 109 | F9: 45123 | G9: 45123.823 | H9: 45124.505 | I9: 45124.523 | J9: 45125.919 | K9: Collected | L9: Standard | M9: Gauteng | N9: 366.6 | O9: 0.57 | P9: 68.15 | Q9: =IF(H9="","",(H9-F9)*24) | R9: =IF(J9="","",(J9-H9)*24)
A10: 16860 | B10: PGO10016860 | C10: 17 | D10: 1894 | E10: 217 | F10: 45125.246 | G10: 45125.641 | H10: 45126.71 | I10: 45126.72 | J10: 45128.059 | K10: Collected | L10: Standard | M10: KwaZulu-Natal | N10: 156.6 | O10: 5.8 | P10: 78.9 | Q10: =IF(H10="","",(H10-F10)*24) | R10: =IF(J10="","",(J10-H10)*24)
A11: 17093 | B11: PGO10017093 | C11: 47 | D11: 1190 | E11: 318 | F11: 45125.518 | G11: 45125.698 | H11: 45126.131 | I11: 45126.149 | J11: 45127.508 | K11: Collected | L11: Standard | M11: Limpopo | N11: 239.97 | O11: 0.5 | P11: 51.6 | Q11: =IF(H11="","",(H11-F11)*24) | R11: =IF(J11="","",(J11-H11)*24)
A12: 4121 | B12: PGO10004121 | C12: 3 | D12: 2698 | E12: 94 | F12: 45127.606 | G12: 45127.701 | H12: 45128.293 | I12: 45128.352 | J12: 45131.801 | K12: Collected | L12: Standard | M12: KwaZulu-Natal | N12: 65.79 | O12: 2.12 | P12: 40.45 | Q12: =IF(H12="","",(H12-F12)*24) | R12: =IF(J12="","",(J12-H12)*24)
A13: 13693 | B13: PGO10013693 | C13: 141 | D13: 1526 | E13: 381 | F13: 45128.146 | G13: 45128.415 | H13: 45129.144 | I13: 45129.192 | J13: 45130.418 | K13: Collected | L13: Standard | M13: North West | N13: 158.37 | O13: 0.84 | P13: 57.41 | Q13: =IF(H13="","",(H13-F13)*24) | R13: =IF(J13="","",(J13-H13)*24)
... A25: 23304 | B25: PGO10023304 | C25: 15 | D25: 276 | E25: 356 | F25: 45148.952 | G25: 45149.497 | H25: 45150.311 | I25: 45150.339 | J25: 45156.909 | K25: Collected | L25: Standard | M25: Gauteng | N25: 1965.48 | O25: 0.36 | P25: 62.71 | Q25: =IF(H25="","",(H25-F25)*24) | R25: =IF(J25="","",(J25-H25)*24)
A26: 37113 | B26: PGO10037113 | C26: 77 | D26: 2413 | E26: 18 | F26: 45149.446 | G26: 45149.523 | H26: 45150.497 | I26: 45150.507 | K26: ExpiredRTS | L26: Express | M26: KwaZulu-Natal | N26: 233.97 | O26: 3.31 | P26: 47.27 | Q26: =IF(H26="","",(H26-F26)*24) | R26: =IF(J26="","",(J26-H26)*24)
A27: 23054 | B27: PGO10023054 | C27: 4 | D27: 3236 | E27: 445 | F27: 45151.987 | G27: 45152.169 | H27: 45152.945 | I27: 45152.998 | J27: 45156.323 | K27: Collected | L27: Standard | M27: Gauteng | N27: 112.91 | O27: 1.03 | P27: 41.74 | Q27: =IF(H27="","",(H27-F27)*24) | R27: =IF(J27="","",(J27-H27)*24)
A28: 33447 | B28: PGO10033447 | C28: 2 | D28: 1297 | E28: 295 | F28: 45152.047 | G28: 45152.26 | H28: 45153.391 | I28: 45153.448 | J28: 45156.73 | K28: Collected | L28: Standard | M28: Eastern Cape | N28: 227.07 | O28: 1.44 | P28: 48.33 | Q28: =IF(H28="","",(H28-F28)*24) | R28: =IF(J28="","",(J28-H28)*24)
A29: 27616 | B29: PGO10027616 | C29: 111 | D29: 3878 | E29: 113 | F29: 45153.058 | G29: 45153.275 | H29: 45153.841 | I29: 45153.869 | J29: 45155.561 | K29: Collected | L29: Express | M29: Gauteng | N29: 269.18 | O29: 1.88 | P29: 62.48 | Q29: =IF(H29="","",(H29-F29)*24) | R29: =IF(J29="","",(J29-H29)*24)
A30: 24162 | B30: PGO10024162 | C30: 3 | D30: 3210 | E30: 317 | F30: 45155.051 | G30: 45155.167 | H30: 45155.681 | I30: 45155.685 | J30: 45156.883 | K30: Collected | L30: Standard | M30: Gauteng | N30: 276.71 | O30: 5.52 | P30: 53.7 | Q30: =IF(H30="","",(H30-F30)*24) | R30: =IF(J30="","",(J30-H30)*24)
A31: 44297 | B31: PGO10044297 | C31: 2 | D31: 3712 | E31: 191 | F31: 45155.751 | G31: 45155.981 | H31: 45156.781 | I31: 45156.838 | J31: 45157.048 | K31: Collected | L31: Standard | M31: Gauteng | N31: 201 | O31: 0.48 | P31: 51.06 | Q31: =IF(H31="","",(H31-F31)*24) | R31: =IF(J31="","",(J31-H31)*24)
A32: 35689 | B32: PGO10035689 | C32: 2 | D32: 676 | E32: 234 | F32: 45161.144 | G32: 45161.304 | H32: 45161.845 | I32: 45161.859 | J32: 45163.413 | K32: Collected | L32: Standard | M32: KwaZulu-Natal | N32: 157.3 | O32: 2.33 | P32: 48.12 | Q32: =IF(H32="","",(H32-F32)*24) | R32: =IF(J32="","",(J32-H32)*24)
A33: 31764 | B33: PGO10031764 | C33: 23 | D33: 1348 | E33: 217 | F33: 45162.827 | G33: 45162.861 | H33: 45164.15 | I33: 45164.187 | J33: 45165.615 | K33: Collected | L33: Standard | M33: KwaZulu-Natal | N33: 429.01 | O33: 5.43 | P33: 67.09 | Q33: =IF(H33="","",(H33-F33)*24) | R33: =IF(J33="","",(J33-H33)*24)
A34: 44982 | B34: PGO10044982 | C34: 26 | D34: 3557 | E34: 291 | F34: 45163.296 | G34: 45163.408 | H34: 45163.877 | I34: 45163.937 | J34: 45165.334 | K34: Collected | L34: Return-to-Retailer | M34: Gauteng | N34: 368.43 | O34: 0.83 | P34: 57.87 | Q34: =IF(H34="","",(H34-F34)*24) | R34: =IF(J34="","",(J34-H34)*24)
A35: 41799 | B35: PGO10041799 | C35: 31 | D35: 3754 | E35: 168 | F35: 45163.469 | G35: 45163.749 | H35: 45164.114 | I35: 45164.138 | J35: 45165.115 | K35: Collected | L35: Standard | M35: Gauteng | N35: 374.53 | O35: 0.11 | P35: 54.74 | Q35: =IF(H35="","",(H35-F35)*24) | R35: =IF(J35="","",(J35-H35)*24)
A36: 41559 | B36: PGO10041559 | C36: 20 | D36: 2177 | E36: 153 | F36: 45163.716 | G36: 45163.988 | H36: 45164.821 | I36: 45164.878 | J36: 45164.902 | K36: Collected | L36: Standard | M36: Limpopo | N36: 85.42 | O36: 0.25 | P36: 56.69 | Q36: =IF(H36="","",(H36-F36)*24) | R36: =IF(J36="","",(J36-H36)*24)
A37: 22952 | B37: PGO10022952 | C37: 3 | D37: 595 | E37: 272 | F37: 45164.15 | G37: 45164.252 | H37: 45165.009 | I37: 45165.049 | J37: 45165.746 | K37: Collected | L37: Standard | M37: Western Cape | N37: 270.01 | O37: 1.06 | P37: 39.28 | Q37: =IF(H37="","",(H37-F37)*24) | R37: =IF(J37="","",(J37-H37)*24)
A38: 36398 | B38: PGO10036398 | C38: 2 | D38: 479 | E38: 152 | F38: 45164.419 | G38: 45164.698 | H38: 45165.583 | I38: 45165.605 | J38: 45166.605 | K38: Collected | L38: Standard | M38: Mpumalanga | N38: 181.34 | O38: 2.61 | P38: 52.11 | Q38: =IF(H38="","",(H38-F38)*24) | R38: =IF(J38="","",(J38-H38)*24)
... A71: 85785 | B71: PGO10085785 | C71: 1 | D71: 162 | E71: 5 | F71: 45208.963 | G71: 45209.023 | H71: 45209.908 | I71: 45209.933 | J71: 45210.045 | K71: Collected | L71: Return-to-Retailer | M71: Gauteng | N71: 291.12 | O71: 0.19 | P71: 47.84 | Q71: =IF(H71="","",(H71-F71)*24) | R71: =IF(J71="","",(J71-H71)*24)
A72: 70243 | B72: PGO10070243 | C72: 78 | D72: 3887 | E72: 350 | F72: 45212.482 | G72: 45212.608 | H72: 45213.078 | I72: 45213.14 | K72: ExpiredRTS | L72: Standard | M72: Gauteng | N72: 144.81 | O72: 0.64 | P72: 66.09 | Q72: =IF(H72="","",(H72-F72)*24) | R72: =IF(J72="","",(J72-H72)*24)
A73: 69708 | B73: PGO10069708 | C73: 1 | D73: 3518 | E73: 379 | F73: 45219.286 | G73: 45219.742 | H73: 45220.017 | I73: 45220.029 | J73: 45222.991 | K73: Collected | L73: Standard | M73: Gauteng | N73: 381.13 | O73: 0.96 | P73: 46.66 | Q73: =IF(H73="","",(H73-F73)*24) | R73: =IF(J73="","",(J73-H73)*24)
A74: 77809 | B74: PGO10077809 | C74: 43 | D74: 3440 | E74: 59 | F74: 45219.907 | G74: 45220.137 | H74: 45220.91 | I74: 45220.92 | J74: 45221.122 | K74: Collected | L74: Express | M74: KwaZulu-Natal | N74: 220.92 | O74: 1.49 | P74: 51.43 | Q74: =IF(H74="","",(H74-F74)*24) | R74: =IF(J74="","",(J74-H74)*24)
A75: 90501 | B75: PGO10090501 | C75: 7 | D75: 2638 | E75: 316 | F75: 45221.676 | G75: 45221.937 | H75: 45222.605 | I75: 45222.615 | J75: 45223.074 | K75: Collected | L75: Standard | M75: KwaZulu-Natal | N75: 73.66 | O75: 2.42 | P75: 47.71 | Q75: =IF(H75="","",(H75-F75)*24) | R75: =IF(J75="","",(J75-H75)*24)
A76: 74697 | B76: PGO10074697 | C76: 6 | D76: 712 | E76: 459 | F76: 45226.293 | G76: 45226.305 | H76: 45226.716 | I76: 45226.752 | J76: 45228.992 | K76: Collected | L76: Standard | M76: Gauteng | N76: 155.58 | O76: 0.45 | P76: 41.8 | Q76: =IF(H76="","",(H76-F76)*24) | R76: =IF(J76="","",(J76-H76)*24)
A77: 89984 | B77: PGO10089984 | C77: 6 | D77: 2127 | E77: 252 | F77: 45226.356 | G77: 45226.686 | H77: 45227.12 | I77: 45227.155 | J77: 45227.595 | K77: Collected | L77: Express | M77: Mpumalanga | N77: 1172.55 | O77: 0.52 | P77: 40.75 | Q77: =IF(H77="","",(H77-F77)*24) | R77: =IF(J77="","",(J77-H77)*24)
A78: 83461 | B78: PGO10083461 | C78: 145 | D78: 2493 | E78: 22 | F78: 45228.752 | G78: 45228.8 | H78: 45229.299 | I78: 45229.306 | J78: 45230.38 | K78: Collected | L78: Standard | M78: Gauteng | N78: 84.54 | O78: 1.65 | P78: 53.64 | Q78: =IF(H78="","",(H78-F78)*24) | R78: =IF(J78="","",(J78-H78)*24)
A79: 75974 | B79: PGO10075974 | C79: 1 | D79: 64 | E79: 102 | F79: 45230.492 | G79: 45230.86 | H79: 45231.168 | I79: 45231.201 | J79: 45233.324 | K79: Collected | L79: Standard | M79: Gauteng | N79: 98.49 | O79: 1.7 | P79: 47.58 | Q79: =IF(H79="","",(H79-F79)*24) | R79: =IF(J79="","",(J79-H79)*24)
A80: 74375 | B80: PGO10074375 | C80: 7 | D80: 2905 | E80: 175 | F80: 45231.086 | G80: 45231.193 | H80: 45232.307 | I80: 45232.332 | J80: 45233.181 | K80: Collected | L80: Standard | M80: Mpumalanga | N80: 7042.62 | O80: 0.64 | P80: 49.59 | Q80: =IF(H80="","",(H80-F80)*24) | R80: =IF(J80="","",(J80-H80)*24)
A81: 100909 | B81: PGO10100909 | C81: 72 | D81: 3729 | E81: 312 | F81: 45235.526 | G81: 45235.571 | H81: 45236.992 | I81: 45237.033 | J81: 45238.408 | K81: Collected | L81: Standard | M81: Western Cape | N81: 162.37 | O81: 1.38 | P81: 61.95 | Q81: =IF(H81="","",(H81-F81)*24) | R81: =IF(J81="","",(J81-H81)*24)
A82: 129996 | B82: PGO10129996 | C82: 11 | D82: 1297 | E82: 355 | F82: 45235.568 | G82: 45235.642 | H82: 45236.648 | I82: 45236.694 | J82: 45237.579 | K82: Collected | L82: Standard | M82: Eastern Cape | N82: 57.45 | O82: 0.61 | P82: 65.7 | Q82: =IF(H82="","",(H82-F82)*24) | R82: =IF(J82="","",(J82-H82)*24)
A83: 119454 | B83: PGO10119454 | C83: 4 | D83: 329 | E83: 175 | F83: 45237.638 | G83: 45237.756 | H83: 45238.928 | I83: 45238.952 | J83: 45239.668 | K83: Collected | L83: Express | M83: Mpumalanga | N83: 494.16 | O83: 1.66 | P83: 44.09 | Q83: =IF(H83="","",(H83-F83)*24) | R83: =IF(J83="","",(J83-H83)*24)
A84: 127789 | B84: PGO10127789 | C84: 23 | D84: 3402 | E84: 79 | F84: 45237.901 | G84: 45238.434 | H84: 45239.339 | I84: 45239.369 | J84: 45242.071 | K84: Collected | L84: Standard | M84: Limpopo | N84: 459.64 | O84: 0.94 | P84: 51.09 | Q84: =IF(H84="","",(H84-F84)*24) | R84: =IF(J84="","",(J84-H84)*24)
... A309: 466608 | B309: PGO10466608 | C309: 84 | D309: 302 | E309: 286 | F309: 45606.468 | G309: 45606.534 | H309: 45607.596 | I309: 45607.637 | J309: 45610.062 | K309: Collected | L309: Return-to-Retailer | M309: Western Cape | N309: 107.22 | O309: 0.82 | P309: 45.39 | Q309: =IF(H309="","",(H309-F309)*24) | R309: =IF(J309="","",(J309-H309)*24)
A310: 466768 | B310: PGO10466768 | C310: 17 | D310: 222 | E310: 57 | F310: 45609.148 | G310: 45609.527 | H310: 45610.132 | I310: 45610.14 | J310: 45611.471 | K310: Collected | L310: Standard | M310: KwaZulu-Natal | N310: 127.88 | P310: 77.84 | Q310: =IF(H310="","",(H310-F310)*24) | R310: =IF(J310="","",(J310-H310)*24)
A311: 468791 | B311: PGO10468791 | C311: 7 | D311: 2431 | E311: 455 | F311: 45611.068 | G311: 45611.292 | H311: 45612.062 | I311: 45612.107 | J311: 45612.271 | K311: Collected | L311: Return-to-Retailer | M311: Western Cape | N311: 638.13 | O311: 0.28 | P311: 48.33 | Q311: =IF(H311="","",(H311-F311)*24) | R311: =IF(J311="","",(J311-H311)*24)
A312: 486261 | B312: PGO10486261 | C312: 10 | D312: 3613 | E312: 354 | F312: 45611.069 | G312: 45611.258 | H312: 45612.622 | I312: 45612.665 | J312: 45614.626 | K312: Collected | L312: Standard | M312: KwaZulu-Natal | N312: 64.4 | O312: 2.92 | P312: 62.3 | Q312: =IF(H312="","",(H312-F312)*24) | R312: =IF(J312="","",(J312-H312)*24)
A313: 439815 | B313: PGO10439815 | C313: 2 | D313: 2553 | E313: 83 | F313: 45611.188 | G313: 45611.545 | H313: 45612.621 | I313: 45612.625 | J313: 45612.93 | K313: Collected | L313: Standard | M313: KwaZulu-Natal | N313: 47.15 | O313: 1.77 | P313: 49.69 | Q313: =IF(H313="","",(H313-F313)*24) | R313: =IF(J313="","",(J313-H313)*24)
A314: 454507 | B314: PGO10454507 | C314: 97 | D314: 1167 | E314: 37 | F314: 45611.541 | G314: 45611.887 | H314: 45612.686 | I314: 45612.709 | J314: 45616.04 | K314: Collected | L314: Standard | M314: Western Cape | N314: 118.69 | O314: 3.37 | P314: 47.2 | Q314: =IF(H314="","",(H314-F314)*24) | R314: =IF(J314="","",(J314-H314)*24)
A315: 467901 | B315: PGO10467901 | C315: 1 | D315: 2030 | E315: 441 | F315: 45613.506 | G315: 45613.647 | H315: 45614.575 | I315: 45614.586 | J315: 45616.657 | K315: Collected | L315: Standard | M315: Northern Cape | N315: 1963.53 | O315: 1.52 | P315: 46 | Q315: =IF(H315="","",(H315-F315)*24) | R315: =IF(J315="","",(J315-H315)*24)
A316: 439820 | B316: PGO10439820 | C316: 1 | D316: 600 | E316: 347 | F316: 45614.266 | G316: 45614.489 | H316: 45615.198 | I316: 45615.213 | J316: 45615.986 | K316: Collected | L316: Standard | M316: Free State | N316: 172.55 | O316: 0.67 | P316: 46.4 | Q316: =IF(H316="","",(H316-F316)*24) | R316: =IF(J316="","",(J316-H316)*24)
A317: 479624 | B317: PGO10479624 | C317: 2 | D317: 960 | E317: 492 | F317: 45615.306 | G317: 45615.603 | H317: 45615.772 | I317: 45615.82 | J317: 45616.445 | K317: Collected | L317: Standard | M317: Gauteng | N317: 115.28 | O317: 1.44 | P317: 48.25 | Q317: =IF(H317="","",(H317-F317)*24) | R317: =IF(J317="","",(J317-H317)*24)
A318: 434443 | B318: PGO10434443 | C318: 84 | D318: 3815 | E318: 431 | F318: 45615.836 | G318: 45616.139 | H318: 45616.546 | I318: 45616.586 | J318: 45617.19 | K318: Collected | L318: Standard | M318: Mpumalanga | N318: 101.9 | O318: 0.31 | P318: 48.16 | Q318: =IF(H318="","",(H318-F318)*24) | R318: =IF(J318="","",(J318-H318)*24)
A319: 474648 | B319: PGO10474648 | C319: 1 | D319: 806 | E319: 291 | F319: 45616.721 | G319: 45616.85 | H319: 45617.738 | I319: 45617.777 | J319: 45619.097 | K319: Collected | L319: Standard | M319: Gauteng | N319: 733.88 | O319: 0.67 | P319: 44.01 | Q319: =IF(H319="","",(H319-F319)*24) | R319: =IF(J319="","",(J319-H319)*24)
A320: 462303 | B320: PGO10462303 | C320: 79 | D320: 2375 | E320: 479 | F320: 45617.644 | G320: 45617.809 | H320: 45618.659 | I320: 45618.691 | J320: 45618.988 | K320: Collected | L320: Standard | M320: Gauteng | N320: 1209.87 | O320: 0.64 | P320: 40.68 | Q320: =IF(H320="","",(H320-F320)*24) | R320: =IF(J320="","",(J320-H320)*24)
A321: 484154 | B321: PGO10484154 | C321: 98 | D321: 857 | E321: 131 | F321: 45617.649 | G321: 45617.873 | H321: 45618.455 | I321: 45618.5 | J321: 45619.833 | K321: Collected | L321: Standard | M321: KwaZulu-Natal | N321: 1068.07 | O321: 0.93 | P321: 63.59 | Q321: =IF(H321="","",(H321-F321)*24) | R321: =IF(J321="","",(J321-H321)*24)
A322: 455552 | B322: PGO10455552 | C322: 18 | D322: 1292 | E322: 127 | F322: 45619.469 | G322: 45619.523 | H322: 45620.075 | I322: 45620.082 | J322: 45622.047 | K322: Collected | L322: Express | M322: Free State | N322: 1399.23 | O322: 4.9 | P322: 42.43 | Q322: =IF(H322="","",(H322-F322)*24) | R322: =IF(J322="","",(J322-H322)*24)
... A330: 460021 | B330: PGO10460021 | C330: 11 | D330: 1628 | E330: 170 | F330: 45623.855 | G330: 45624.081 | H330: 45624.764 | I330: 45624.824 | J330: 45626.106 | K330: Collected | L330: Standard | M330: Limpopo | N330: 136.87 | O330: 0.36 | P330: 69.28 | Q330: =IF(H330="","",(H330-F330)*24) | R330: =IF(J330="","",(J330-H330)*24)
A331: 476530 | B331: PGO10476530 | C331: 1 | D331: 3288 | E331: 347 | F331: 45624.692 | G331: 45625.062 | H331: 45626.19 | I331: 45626.221 | K331: ExpiredRTS | L331: Standard | M331: Free State | N331: 596.29 | O331: 0.53 | P331: 48.11 | Q331: =IF(H331="","",(H331-F331)*24) | R331: =IF(J331="","",(J331-H331)*24)
A332: 476978 | B332: PGO10476978 | C332: 98 | D332: 3115 | E332: 24 | F332: 45624.699 | G332: 45624.875 | H332: 45625.305 | I332: 45625.322 | J332: 45626.288 | K332: Collected | L332: Standard | M332: Limpopo | N332: 1262.1 | O332: 3.61 | P332: 63.3 | Q332: =IF(H332="","",(H332-F332)*24) | R332: =IF(J332="","",(J332-H332)*24)
A333: 478556 | B333: PGO10478556 | C333: 3 | D333: 3137 | E333: 23 | F333: 45625.626 | G333: 45626.02 | H333: 45626.815 | I333: 45626.825 | J333: 45627.253 | K333: Collected | L333: Standard | M333: Gauteng | N333: 172.32 | O333: 1 | P333: 38 | Q333: =IF(H333="","",(H333-F333)*24) | R333: =IF(J333="","",(J333-H333)*24)
A334: 477942 | B334: PGO10477942 | C334: 107 | D334: 1250 | E334: 173 | F334: 45625.686 | G334: 45625.812 | H334: 45626.954 | I334: 45626.978 | J334: 45630.072 | K334: Collected | L334: Standard | M334: Western Cape | N334: 142.27 | O334: 2.68 | P334: 55.9 | Q334: =IF(H334="","",(H334-F334)*24) | R334: =IF(J334="","",(J334-H334)*24)
A335: 523507 | B335: PGO10523507 | C335: 1 | D335: 2064 | E335: 106 | F335: 45629.928 | G335: 45630.15 | H335: 45630.809 | I335: 45630.818 | J335: 45631.435 | K335: Collected | L335: Standard | M335: Gauteng | N335: 159.85 | O335: 2.18 | P335: 44.21 | Q335: =IF(H335="","",(H335-F335)*24) | R335: =IF(J335="","",(J335-H335)*24)
A336: 523123 | B336: PGO10523123 | C336: 26 | D336: 3609 | E336: 156 | F336: 45630.86 | G336: 45631.483 | H336: 45632.065 | I336: 45632.081 | J336: 45634.173 | K336: Collected | L336: Standard | M336: Mpumalanga | N336: 297.97 | O336: 0.72 | P336: 57.7 | Q336: =IF(H336="","",(H336-F336)*24) | R336: =IF(J336="","",(J336-H336)*24)
A337: 497173 | B337: PGO10497173 | C337: 23 | D337: 350 | E337: 181 | F337: 45631.013 | G337: 45631.425 | H337: 45631.976 | I337: 45632.012 | J337: 45632.86 | K337: Collected | L337: Standard | M337: Free State | N337: 126.39 | O337: 0.64 | P337: 50.71 | Q337: =IF(H337="","",(H337-F337)*24) | R337: =IF(J337="","",(J337-H337)*24)
A338: 494270 | B338: PGO10494270 | C338: 17 | D338: 1167 | E338: 140 | F338: 45631.364 | G338: 45631.779 | H338: 45632.574 | I338: 45632.583 | J338: 45632.85 | K338: Collected | L338: Standard | M338: Western Cape | N338: 142.7 | O338: 0.75 | P338: 56.45 | Q338: =IF(H338="","",(H338-F338)*24) | R338: =IF(J338="","",(J338-H338)*24)
A339: 523257 | B339: PGO10523257 | C339: 63 | D339: 2991 | E339: 422 | F339: 45631.996 | G339: 45632.106 | H339: 45633.101 | I339: 45633.108 | J339: 45634.283 | K339: Collected | L339: Express | M339: KwaZulu-Natal | N339: 586.59 | O339: 1.02 | P339: 52.49 | Q339: =IF(H339="","",(H339-F339)*24) | R339: =IF(J339="","",(J339-H339)*24)
A340: 512826 | B340: PGO10512826 | C340: 76 | D340: 2617 | E340: 295 | F340: 45633.787 | G340: 45633.925 | H340: 45634.674 | I340: 45634.679 | J340: 45634.825 | K340: Collected | L340: Standard | M340: Eastern Cape | N340: 456.23 | O340: 1.59 | P340: 56.76 | Q340: =IF(H340="","",(H340-F340)*24) | R340: =IF(J340="","",(J340-H340)*24)
A341: 522252 | B341: PGO10522252 | C341: 1 | D341: 1430 | E341: 113 | F341: 45637.356 | G341: 45637.865 | H341: 45638.847 | I341: 45638.88 | J341: 45640.188 | K341: Collected | L341: Return-to-Retailer | M341: Gauteng | N341: 144.64 | O341: 6.19 | P341: 63.43 | Q341: =IF(H341="","",(H341-F341)*24) | R341: =IF(J341="","",(J341-H341)*24)
A342: 497003 | B342: PGO10497003 | C342: 24 | D342: 3668 | E342: 33 | F342: 45641.131 | G342: 45641.556 | H342: 45642.538 | I342: 45642.594 | J342: 45644.997 | K342: Collected | L342: Standard | M342: Free State | N342: 55.42 | O342: 0.86 | P342: 60.24 | Q342: =IF(H342="","",(H342-F342)*24) | R342: =IF(J342="","",(J342-H342)*24)
A343: 509840 | B343: PGO10509840 | C343: 77 | D343: 2110 | E343: 5 | F343: 45641.832 | G343: 45642.025 | H343: 45642.752 | I343: 45642.773 | J343: 45643.031 | K343: Collected | L343: Standard | M343: Gauteng | N343: 426.75 | O343: 1.59 | P343: 49.62 | Q343: =IF(H343="","",(H343-F343)*24) | R343: =IF(J343="","",(J343-H343)*24)
... A499: 709285 | B499: PGO10709285 | C499: 127 | D499: 3928 | E499: 27 | F499: 45839.507 | G499: 45839.599 | H499: 45840.305 | I499: 45840.321 | J499: 45840.476 | K499: Collected | L499: Express | M499: Western Cape | N499: 173.71 | O499: 5.34 | P499: 83.58 | Q499: =IF(H499="","",(H499-F499)*24) | R499: =IF(J499="","",(J499-H499)*24)
A500: 722972 | B500: PGO10722972 | C500: 1 | D500: 1969 | E500: 19 | F500: 45839.59 | G500: 45839.77 | H500: 45840.341 | I500: 45840.355 | K500: ExpiredRTS | L500: Standard | M500: North West | N500: 246.84 | O500: 1.95 | P500: 44.21 | Q500: =IF(H500="","",(H500-F500)*24) | R500: =IF(J500="","",(J500-H500)*24)
A501: 723719 | B501: PGO10723719 | C501: 3 | D501: 1408 | E501: 410 | F501: 45840.003 | G501: 45840.073 | H501: 45841.634 | I501: 45841.69 | J501: 45842.491 | K501: Collected | L501: Standard | M501: KwaZulu-Natal | N501: 606.37 | O501: 1 | P501: 39.65 | Q501: =IF(H501="","",(H501-F501)*24) | R501: =IF(J501="","",(J501-H501)*24)
A502: 718967 | B502: PGO10718967 | C502: 1 | D502: 228 | E502: 370 | F502: 45840.086 | G502: 45840.43 | H502: 45841.681 | I502: 45841.735 | J502: 45843.918 | K502: Collected | L502: Standard | M502: Free State | N502: 324.88 | O502: 1.64 | P502: 48.21 | Q502: =IF(H502="","",(H502-F502)*24) | R502: =IF(J502="","",(J502-H502)*24)
A503: 739508 | B503: PGO10739508 | C503: 35 | D503: 1119 | E503: 416 | F503: 45843.494 | G503: 45843.762 | H503: 45844.589 | I503: 45844.626 | J503: 45845.55 | K503: Collected | L503: Standard | M503: KwaZulu-Natal | N503: 470.71 | O503: 0.65 | P503: 38.99 | Q503: =IF(H503="","",(H503-F503)*24) | R503: =IF(J503="","",(J503-H503)*24)
A504: 723474 | B504: PGO10723474 | C504: 18 | D504: 2149 | E504: 371 | F504: 45844.077 | G504: 45844.611 | H504: 45845.137 | I504: 45845.185 | J504: 45846.964 | K504: Collected | L504: Standard | M504: Limpopo | N504: 185.43 | O504: 0.99 | P504: 45.42 | Q504: =IF(H504="","",(H504-F504)*24) | R504: =IF(J504="","",(J504-H504)*24)
A505: 734356 | B505: PGO10734356 | C505: 77 | D505: 343 | E505: 108 | F505: 45845.764 | G505: 45846.086 | H505: 45846.735 | I505: 45846.752 | J505: 45847.272 | K505: Collected | L505: Standard | M505: North West | N505: 546.19 | O505: 1.33 | P505: 50.82 | Q505: =IF(H505="","",(H505-F505)*24) | R505: =IF(J505="","",(J505-H505)*24)
A506: 733683 | B506: PGO10733683 | C506: 1 | D506: 3787 | E506: 431 | F506: 45846.738 | G506: 45847.009 | H506: 45847.476 | I506: 45847.486 | J506: 45849.631 | K506: Collected | L506: Standard | M506: Mpumalanga | N506: 617.06 | O506: 0.89 | P506: 44.84 | Q506: =IF(H506="","",(H506-F506)*24) | R506: =IF(J506="","",(J506-H506)*24)
A507: 719684 | B507: PGO10719684 | C507: 7 | D507: 3450 | E507: 325 | F507: 45847.383 | G507: 45847.647 | H507: 45849.35 | I507: 45849.362 | J507: 45850.931 | K507: Collected | L507: Standard | M507: Western Cape | N507: 145.71 | O507: 1.22 | P507: 51.4 | Q507: =IF(H507="","",(H507-F507)*24) | R507: =IF(J507="","",(J507-H507)*24)
A508: 748973 | B508: PGO10748973 | C508: 23 | D508: 1807 | E508: 316 | F508: 45853.531 | G508: 45853.873 | H508: 45854.661 | I508: 45854.674 | J508: 45856.634 | K508: Collected | L508: Standard | M508: KwaZulu-Natal | N508: 319.95 | O508: 1.48 | P508: 49.5 | Q508: =IF(H508="","",(H508-F508)*24) | R508: =IF(J508="","",(J508-H508)*24)
A509: 727275 | B509: PGO10727275 | C509: 23 | D509: 1257 | E509: 351 | F509: 45857.084 | G509: 45857.157 | H509: 45857.698 | I509: 45857.745 | J509: 45859.872 | K509: Collected | L509: Standard | M509: Western Cape | N509: 186.72 | O509: 3.43 | P509: 48.16 | Q509: =IF(H509="","",(H509-F509)*24) | R509: =IF(J509="","",(J509-H509)*24)
A510: 736684 | B510: PGO10736684 | C510: 2 | D510: 1824 | E510: 144 | F510: 45857.292 | G510: 45857.583 | H510: 45857.999 | I510: 45858.019 | J510: 45858.451 | K510: Collected | L510: Standard | M510: Mpumalanga | N510: 141.81 | O510: 0.68 | P510: 49.36 | Q510: =IF(H510="","",(H510-F510)*24) | R510: =IF(J510="","",(J510-H510)*24)
A511: 745481 | B511: PGO10745481 | C511: 43 | D511: 780 | E511: 490 | F511: 45857.319 | G511: 45858.007 | H511: 45858.509 | I511: 45858.529 | J511: 45861.124 | K511: Collected | L511: Standard | M511: Gauteng | N511: 249.3 | O511: 1.62 | P511: 51.23 | Q511: =IF(H511="","",(H511-F511)*24) | R511: =IF(J511="","",(J511-H511)*24)
A512: 748983 | B512: PGO10748983 | C512: 2 | D512: 1367 | E512: 161 | F512: 45857.984 | G512: 45858.218 | H512: 45858.815 | I512: 45858.837 | J512: 45858.937 | K512: Collected | L512: Standard | M512: Gauteng | N512: 153.41 | O512: 0.79 | P512: 50.84 | Q512: =IF(H512="","",(H512-F512)*24) | R512: =IF(J512="","",(J512-H512)*24)
... A635: 887575 | B635: PGO10887575 | C635: 4 | D635: 1432 | E635: 203 | F635: 45972.158 | G635: 45972.244 | H635: 45973.131 | I635: 45973.174 | J635: 45974.56 | K635: Collected | L635: Standard | M635: KwaZulu-Natal | N635: 1086.04 | O635: 0.42 | P635: 41.73 | Q635: =IF(H635="","",(H635-F635)*24) | R635: =IF(J635="","",(J635-H635)*24)
A636: 889407 | B636: PGO10889407 | C636: 1 | D636: 286 | E636: 210 | F636: 45972.229 | G636: 45972.334 | H636: 45973.08 | I636: 45973.091 | K636: ExpiredRTS | L636: Return-to-Retailer | M636: KwaZulu-Natal | N636: 132.92 | O636: 0.38 | P636: 46.13 | Q636: =IF(H636="","",(H636-F636)*24) | R636: =IF(J636="","",(J636-H636)*24)
A637: 869810 | B637: PGO10869810 | C637: 12 | D637: 932 | E637: 338 | F637: 45973.006 | G637: 45973.242 | H637: 45973.946 | I637: 45973.97 | J637: 45974.979 | K637: Collected | L637: Standard | M637: Eastern Cape | N637: 221.06 | O637: 0.44 | P637: 68.53 | Q637: =IF(H637="","",(H637-F637)*24) | R637: =IF(J637="","",(J637-H637)*24)
A638: 899082 | B638: PGO10899082 | C638: 2 | D638: 3546 | E638: 479 | F638: 45973.46 | G638: 45973.724 | H638: 45974.086 | I638: 45974.093 | J638: 45975.028 | K638: Collected | L638: Standard | M638: Gauteng | N638: 821.62 | O638: 0.87 | P638: 50.84 | Q638: =IF(H638="","",(H638-F638)*24) | R638: =IF(J638="","",(J638-H638)*24)
A639: 921079 | B639: PGO10921079 | C639: 91 | D639: 3695 | E639: 150 | F639: 45978.135 | G639: 45978.339 | H639: 45978.699 | I639: 45978.735 | J639: 45979.797 | K639: Collected | L639: Express | M639: Western Cape | N639: 337.15 | O639: 1.48 | P639: 38.8 | Q639: =IF(H639="","",(H639-F639)*24) | R639: =IF(J639="","",(J639-H639)*24)
A640: 898731 | B640: PGO10898731 | C640: 17 | D640: 3769 | E640: 120 | F640: 45978.152 | G640: 45978.168 | H640: 45978.965 | I640: 45979.01 | J640: 45981.362 | K640: Collected | L640: Standard | M640: Mpumalanga | N640: 532.4 | O640: 0.73 | P640: 56.65 | Q640: =IF(H640="","",(H640-F640)*24) | R640: =IF(J640="","",(J640-H640)*24)
A641: 927117 | B641: PGO10927117 | C641: 43 | D641: 2373 | E641: 95 | F641: 45978.316 | G641: 45978.448 | H641: 45979.67 | I641: 45979.716 | J641: 45980.338 | K641: Collected | L641: Standard | M641: Eastern Cape | N641: 418.83 | O641: 1.74 | P641: 51.18 | Q641: =IF(H641="","",(H641-F641)*24) | R641: =IF(J641="","",(J641-H641)*24)
A642: 882058 | B642: PGO10882058 | C642: 23 | D642: 3224 | E642: 434 | F642: 45978.526 | G642: 45978.904 | H642: 45979.522 | I642: 45979.582 | J642: 45980.482 | K642: Collected | L642: Return-to-Retailer | M642: Mpumalanga | N642: 152.52 | O642: 1.03 | P642: 47.18 | Q642: =IF(H642="","",(H642-F642)*24) | R642: =IF(J642="","",(J642-H642)*24)
A643: 916609 | B643: PGO10916609 | C643: 58 | D643: 2905 | E643: 175 | F643: 45979.451 | G643: 45979.811 | H643: 45980.707 | I643: 45980.714 | J643: 45982.69 | K643: Collected | L643: Express | M643: Mpumalanga | N643: 90.02 | O643: 0.7 | P643: 46.24 | Q643: =IF(H643="","",(H643-F643)*24) | R643: =IF(J643="","",(J643-H643)*24)
A644: 922129 | B644: PGO10922129 | C644: 7 | D644: 3215 | E644: 349 | F644: 45979.929 | G644: 45980.015 | H644: 45980.441 | I644: 45980.497 | J644: 45981.348 | K644: Collected | L644: Standard | M644: Gauteng | N644: 300.82 | O644: 0.77 | P644: 48.92 | Q644: =IF(H644="","",(H644-F644)*24) | R644: =IF(J644="","",(J644-H644)*24)
A645: 873285 | B645: PGO10873285 | C645: 51 | D645: 3334 | E645: 140 | F645: 45980.341 | G645: 45980.88 | H645: 45981.976 | I645: 45982.007 | J645: 45982.385 | K645: Collected | L645: Standard | M645: Western Cape | N645: 87.13 | O645: 0.18 | P645: 55.53 | Q645: =IF(H645="","",(H645-F645)*24) | R645: =IF(J645="","",(J645-H645)*24)
A646: 868613 | B646: PGO10868613 | C646: 145 | D646: 3041 | E646: 87 | F646: 45980.349 | G646: 45980.809 | H646: 45981.12 | I646: 45981.159 | J646: 45982.804 | K646: Collected | L646: Standard | M646: Gauteng | N646: 3549.12 | O646: 0.42 | P646: 57.81 | Q646: =IF(H646="","",(H646-F646)*24) | R646: =IF(J646="","",(J646-H646)*24)
A647: 874456 | B647: PGO10874456 | C647: 144 | D647: 3297 | E647: 59 | F647: 45980.643 | G647: 45980.848 | H647: 45981.919 | I647: 45981.97 | J647: 45983.312 | K647: Collected | L647: Standard | M647: KwaZulu-Natal | N647: 252.35 | O647: 3.04 | P647: 44.14 | Q647: =IF(H647="","",(H647-F647)*24) | R647: =IF(J647="","",(J647-H647)*24)
A648: 883111 | B648: PGO10883111 | C648: 1 | D648: 1321 | E648: 299 | F648: 45980.748 | G648: 45980.839 | H648: 45981.967 | I648: 45981.98 | J648: 45985.227 | K648: Collected | L648: Standard | M648: Eastern Cape | N648: 930.88 | O648: 1.54 | P648: 45.64 | Q648: =IF(H648="","",(H648-F648)*24) | R648: =IF(J648="","",(J648-H648)*24)
... A871: 1162291 | B871: PGO11162291 | C871: 2 | D871: 2542 | E871: 438 | F871: 46196.228 | G871: 46196.459 | H871: 46197.565 | I871: 46197.582 | J871: 46198.882 | K871: Collected | L871: Standard | M871: KwaZulu-Natal | N871: 159.24 | O871: 3.56 | P871: 47.66 | Q871: =IF(H871="","",(H871-F871)*24) | R871: =IF(J871="","",(J871-H871)*24)

Sheet Tracking Events Sample
A1: tracking_event_id | B1: parcel_id | C1: event_type | D1: event_timestamp | E1: latitude | F1: longitude | G1: status | H1: source_system | I1: month | J1: year
A2: 48260 | B2: 2650 | C2: AtHub | D2: 45115.649 | E2: -31.145083 | F2: 20.895831 | G2: Open | H2: API | I2: 07 | J2: 2023
A3: 120871 | B3: 6899 | C3: CustomerNotified | D3: 45116.335 | E3: -32.301949 | F3: 18.13506 | G3: Open | H3: ScannerApp | I3: 07 | J3: 2023
A4: 66277 | B4: 20667 | C4: AtHub | D4: 45117.234 | E4: -27.358276 | F4: 27.969543 | G4: Open | H4: PartnerPOS | I4: 07 | J4: 2023
A5: 119770 | B5: 5795 | C5: CustomerNotified | D5: 45118.128 | E5: -32.887358 | F5: 22.89965 | G5: Open | H5: ScannerApp | I5: 07 | J5: 2023
A6: 142280 | B6: 5971 | C6: CollectedByCustomer | D6: 45119.555 | E6: -30.405048 | F6: 18.797544 | G6: Closed | H6: CourierGPS | I6: 07 | J6: 2023
A7: 154550 | B7: 19263 | C7: CollectedByCustomer | D7: 45120.564 | E7: -31.884315 | F7: 28.564855 | G7: Closed | H7: ScannerApp | I7: 07 | J7: 2023
A8: 100864 | B8: 9663 | C8: ArrivedAtPickupPoint | D8: 45122.081 | E8: -25.931499 | F8: 31.33677 | G8: Open | H8: ScannerApp | I8: 07 | J8: 2023
A9: 23718 | B9: 913 | C9: CollectedFromRetailer | D9: 45122.801 | E9: -28.141681 | F9: 31.707802 | G9: Open | H9: API | I9: 07 | J9: 2023
A10: 103434 | B10: 12237 | C10: ArrivedAtPickupPoint | D10: 45122.976 | E10: -26.377128 | F10: 27.247982 | G10: Open | H10: PartnerPOS | I10: 07 | J10: 2023
A11: 28216 | B11: 5411 | C11: CollectedFromRetailer | D11: 45128.268 | E11: -27.502123 | F11: 27.83833 | G11: Open | H11: API | I11: 07 | J11: 2023
A12: 103683 | B12: 12487 | C12: ArrivedAtPickupPoint | D12: 45129.002 | E12: -33.722387 | F12: 19.024572 | G12: Open | H12: PartnerPOS | I12: 07 | J12: 2023
A13: 119730 | B13: 5755 | C13: CustomerNotified | D13: 45129.709 | E13: -25.201989 | F13: 27.340555 | G13: Open | H13: PartnerPOS | I13: 07 | J13: 2023
... A1001: 8360464 | B1001: 1194880 | C1001: CollectedByCustomer | D1001: 46204.706 | E1001: -26.867855 | F1001: 27.020902 | G1001: Closed | H1001: ScannerApp | I1001: 06 | J1001: 2026

Sheet Returns Sample
A1: return_id | B1: parcel_id | C1: retailer_id | D1: return_initiated_at | E1: return_reason | F1: return_value_zar | G1: drop_off_point_id | H1: month | I1: year
A2: 751 | B2: 10341 | C2: 149 | D2: 45114.37 | E2: Wrong size | F2: 176.89 | G2: 433 | H2: 07 | I2: 2023
A3: 1034 | B3: 14234 | C3: 56 | D3: 45118.922 | E3: Wrong size | F3: 370.29 | G3: 1873 | H3: 07 | I3: 2023
A4: 677 | B4: 9130 | C4: 82 | D4: 45121.684 | E4: Wrong size | F4: 288.67 | G4: 2212 | H4: 07 | I4: 2023
A5: 64 | B5: 983 | C5: 1 | D5: 45122.463 | E5: Wrong size | F5: 232.09 | G5: 2911 | H5: 07 | I5: 2023
A6: 676 | B6: 9099 | C6: 3 | D6: 45137.966 | E6: Wrong size | F6: 246.79 | G6: 579 | H6: 07 | I6: 2023
A7: 1557 | B7: 21459 | C7: 65 | D7: 45138.018 | E7: Changed mind | F7: 22.21 | G7: 3554 | H7: 07 | I7: 2023
A8: 462 | B8: 6101 | C8: 7 | D8: 45139.489 | E8: Changed mind | F8: 292.11 | G8: 1828 | H8: 07 | I8: 2023
A9: 1206 | B9: 16892 | C9: 4 | D9: 45143.46 | E9: Wrong size | F9: 69.71 | G9: 2969 | H9: 07 | I9: 2023
A10: 672 | B10: 9069 | C10: 29 | D10: 45144.006 | E10: Wrong size | F10: 79.36 | G10: 3585 | H10: 07 | I10: 2023
A11: 2571 | B11: 35912 | C11: 1 | D11: 45154.003 | E11: Changed mind | F11: 1859.6 | G11: 778 | H11: 08 | I11: 2023
A12: 2426 | B12: 34003 | C12: 7 | D12: 45157.936 | E12: Wrong size | F12: 422.41 | G12: 2146 | H12: 08 | I12: 2023
A13: 2469 | B13: 34599 | C13: 5 | D13: 45158.089 | E13: Item damaged | F13: 548.11 | G13: 2064 | H13: 08 | I13: 2023
... A501: 83371 | B501: 1162683 | C501: 52 | D501: 46205.318 | E501: Wrong size | F501: 48.08 | G501: 2973 | H501: 06 | I501: 2026

Sheet Monthly Volumes
A1: month | B1: parcels | C1: avg_delivery_hours | D1: delivered | E1: rts | F1: lost
A2: 2023-07 | B2: 22309 | C2: 26.9 | D2: 20625 | E2: 1236 | F2: 39
A3: 2023-08 | B3: 22338 | C3: 26.9 | D3: 20645 | E3: 1208 | F3: 38
A4: 2023-09 | B4: 22750 | C4: 27 | D4: 20972 | E4: 1273 | F4: 48
A5: 2023-10 | B5: 23406 | C5: 26.8 | D5: 21610 | E5: 1271 | F5: 40
A6: 2023-11 | B6: 43780 | C6: 26.8 | D6: 40397 | E6: 2430 | F6: 67
A7: 2023-12 | B7: 35682 | C7: 26.8 | D7: 32885 | E7: 1997 | F7: 71
A8: 2024-01 | B8: 17870 | C8: 26.9 | D8: 16433 | E8: 1006 | F8: 39
A9: 2024-02 | B9: 20306 | C9: 27 | D9: 18669 | E9: 1171 | F9: 44
A10: 2024-03 | B10: 26010 | C10: 27 | D10: 23969 | E10: 1450 | F10: 52
A11: 2024-04 | B11: 26601 | C11: 26.9 | D11: 24524 | E11: 1487 | F11: 68
A12: 2024-05 | B12: 27173 | C12: 26.9 | D12: 25104 | E12: 1494 | F12: 58
A13: 2024-06 | B13: 27720 | C13: 26.8 | D13: 25550 | E13: 1553 | F13: 50
... A37: 2026-06 | B37: 40812 | C37: 26.9 | D37: 34003 | E37: 1977 | F37: 76
A38: TOTAL / AVG | B38: =SUM(B2:B37) | C38: =AVERAGE(C2:C37) | D38: =SUM(D2:D37) | E38: =SUM(E2:E37) | F38: =SUM(F2:F37)

Sheet Retailers
A1: retailer_id | B1: retailer_name | C1: industry | D1: tier | E1: contract_start_date | F1: rate_per_parcel_zar | G1: integration_type
A2: 1 | B2: Bash | C2: Fashion & Apparel | D2: Enterprise | E2: 45108 | F2: 46.24 | G2: API
A3: 2 | B3: Woolworths | C3: Retail - Premium | D3: Enterprise | E3: 43705 | F3: 49.85 | G3: API
A4: 3 | B4: Clicks | C4: Health & Pharmacy | D4: Enterprise | E4: 43683 | F4: 38.81 | G4: API
A5: 4 | B5: Sportscene | C5: Fashion & Apparel | D5: Enterprise | E5: 43738 | F5: 43.23 | G5: WooCommerce Plugin
A6: 5 | B6: FILA South Africa | C6: Fashion & Apparel | D6: Mid-Market | E6: 44742 | F6: 56.77 | G6: API
A7: 6 | B7: Cape Union Mart | C7: Outdoor & Lifestyle | D7: Enterprise | E7: 44560 | F7: 40.26 | G7: WooCommerce Plugin
A8: 7 | B8: OneDayOnly | C8: E-commerce Marketplace | D8: Enterprise | E8: 45108 | F8: 49.43 | G8: Manual Portal
A9: 8 | B9: Loot.co.za | C9: E-commerce Marketplace | D9: Mid-Market | E9: 44164 | F9: 56.11 | G9: API
A10: 9 | B10: Wellness Warehouse | C10: Health & Pharmacy | D10: Mid-Market | E10: 43822 | F10: 57.54 | G10: API
A11: 10 | B11: Griffiths SA | C11: Home & Garden | D11: SMB | E11: 43226 | F11: 63.29 | G11: Shopify Plugin
A12: 11 | B12: Newman Ltd Direct | C12: Retail - Premium | D12: SMB | E12: 43119 | F12: 67.44 | G12: API
A13: 12 | B13: Norman Online | C13: Fashion & Apparel | D13: SMB | E13: 44055 | F13: 68.21 | G13: API
... A151: 150 | B151: Kennedy Inc Direct | C151: Fashion & Apparel | D151: Mid-Market | E151: 45052 | F151: 54.14 | G151: API

Sheet Pickup Points Sample
A1: pickup_point_id | B1: store_name | C1: partner_name | D1: province | E1: city | F1: latitude | G1: longitude | H1: opening_date | I1: capacity_per_day | J1: status
A2: 314 | B2: Clicks Newcastle Mall | C2: Clicks | D2: KwaZulu-Natal | E2: Newcastle | F2: -27.384111 | G2: 29.026651 | H2: 44220 | I2: 35 | J2: Active
A3: 3489 | B3: Clicks Umhlanga | C3: Clicks | D3: KwaZulu-Natal | E3: Umhlanga | F3: -27.951628 | G3: 29.043078 | H3: 42447 | I3: 35 | J3: Active
A4: 2731 | B4: Lewis Polokwane Square | C4: Lewis | D4: Limpopo | E4: Polokwane | F4: -22.885509 | G4: 27.416431 | H4: 44684 | I4: 50 | J4: Active
A5: 193 | B5: PEP Tzaneen Central | C5: PEP | D5: Limpopo | E5: Tzaneen | F5: -22.343412 | G5: 30.84085 | H5: 44305 | I5: 20 | J5: Active
A6: 3066 | B6: PostNet Mokopane Plaza | C6: PostNet | D6: Limpopo | E6: Mokopane | F6: -24.688662 | G6: 27.152757 | H6: 44639 | I6: 80 | J6: Active
A7: 1374 | B7: Caltex Freshstop Roodepoort Mall | C7: Caltex Freshstop | D7: Gauteng | E7: Roodepoort | F7: -25.207415 | G7: 27.486037 | H7: 42702 | I7: 80 | J7: Active
A8: 2056 | B8: Clicks Cape Town | C8: Clicks | D8: Western Cape | E8: Cape Town | F8: -32.155526 | G8: 20.092185 | H8: 44183 | I8: 35 | J8: Active
A9: 3343 | B9: PEP Somerset West Central | C9: PEP | D9: Western Cape | E9: Somerset West | F9: -31.632267 | G9: 22.07496 | H9: 43642 | I9: 120 | J9: Active
A10: 552 | B10: Clicks Bellville | C10: Clicks | D10: Western Cape | E10: Bellville | F10: -32.691228 | G10: 21.068475 | H10: 43325 | I10: 80 | J10: Active
A11: 3863 | B11: Build it Mokopane Park | C11: Build it | D11: Limpopo | E11: Mokopane | F11: -24.892049 | G11: 30.306525 | H11: 44791 | I11: 35 | J11: Active
A12: 753 | B12: Clicks Cape Town Park | C12: Clicks | D12: Western Cape | E12: Cape Town | F12: -33.631004 | G12: 22.582231 | H12: 44326 | I12: 20 | J12: Active
A13: 1548 | B13: Build it Bellville Square | C13: Build it | D13: Western Cape | E13: Bellville | F13: -31.598204 | G13: 18.468107 | H13: 42869 | I13: 120 | J13: Active
... A501: 2599 | B501: Lewis Pretoria Park | C501: Lewis | D501: Gauteng | E501: Pretoria | F501: -25.48058 | G501: 28.16476 | H501: 44500 | I501: 80 | J501: Active

Sheet Customers Sample
A1: customer_id | B1: customer_name | C1: mobile_number | D1: province | E1: city | F1: registration_date | G1: customer_segment | H1: active_flag
A2: 56103 | B2: Nomvula Mokoena | C2: +27475272027 | D2: Western Cape | E2: Somerset West | F2: 45654 | G2: Occasional | H2: =FALSE()
A3: 240102 | B3: Naledi Venter | C3: +27475619679 | D3: Northern Cape | E3: Kimberley | F3: 44968 | G3: Frequent | H3: =TRUE()
A4: 397221 | B4: Refilwe Pretorius | C4: +27472485583 | D4: Eastern Cape | E4: East London | F4: 44444 | G4: Dormant | H4: =TRUE()
A5: 245223 | B5: Chloe Tshabalala | C5: +27478125850 | D5: KwaZulu-Natal | E5: Durban | F5: 45328 | G5: Occasional | H5: =TRUE()
A6: 81961 | B6: Johan Fourie | C6: +27473348452 | D6: KwaZulu-Natal | E6: Durban | F6: 45443 | G6: Occasional | H6: =TRUE()
A7: 329319 | B7: Chloe Pretorius | C7: +27475700838 | D7: Gauteng | E7: Johannesburg | F7: 45950 | G7: Dormant | H7: =TRUE()
A8: 183559 | B8: Fatima Zulu | C8: +27479417885 | D8: Eastern Cape | E8: Mthatha | F8: 45931 | G8: Occasional | H8: =TRUE()
A9: 79163 | B9: Riaan Venter | C9: +27473516308 | D9: Mpumalanga | E9: Middelburg | F9: 45063 | G9: Frequent | H9: =TRUE()
A10: 138982 | B10: Dineo Ngcobo | C10: +27473895160 | D10: Eastern Cape | E10: Mthatha | F10: 45157 | G10: Occasional | H10: =TRUE()
A11: 243314 | B11: Zanele Pretorius | C11: +27475897500 | D11: North West | E11: Klerksdorp | F11: 45104 | G11: Regular | H11: =TRUE()
A12: 271725 | B12: Khanyi Dlamini | C12: +27472325079 | D12: Free State | E12: Welkom | F12: 45359 | G12: Occasional | H12: =TRUE()
A13: 223228 | B13: Kagiso Smith | C13: +27474748698 | D13: Western Cape | E13: Paarl | F13: 44587 | G13: Dormant | H13: =TRUE()
A14: 339752 | B14: Liam Mabaso | C14: +27479785422 | D14: Western Cape | E14: Table View | F14: 44918 | G14: Occasional | H14: =TRUE()
... A24: 43550 | B24: Lerato Botha | C24: +27471390516 | D24: Western Cape | E24: Somerset West | F24: 45346 | G24: Dormant | H24: =TRUE()
A25: 37471 | B25: Pieter Mahlangu | C25: +27476650829 | D25: Western Cape | E25: Paarl | F25: 46198 | G25: Frequent | H25: =FALSE()
A26: 45761 | B26: Daniel Zulu | C26: +27479220332 | D26: Western Cape | E26: George | F26: 45103 | G26: Regular | H26: =TRUE()
A27: 257827 | B27: Zanele Pillay | C27: +27477102531 | D27: Western Cape | E27: George | F27: 44943 | G27: Dormant | H27: =TRUE()
A28: 320287 | B28: Mandla Ngcobo | C28: +27477011744 | D28: Free State | E28: Bloemfontein | F28: 45155 | G28: Occasional | H28: =TRUE()
A29: 315444 | B29: Bongani Adams | C29: +27472070911 | D29: Limpopo | E29: Tzaneen | F29: 46073 | G29: Regular | H29: =TRUE()
A30: 101907 | B30: Nomvula Steyn | C30: +27475236898 | D30: Eastern Cape | E30: Uitenhage | F30: 44424 | G30: Occasional | H30: =FALSE()
A31: 199351 | B31: Dineo Fourie | C31: +27471173295 | D31: Eastern Cape | E31: Gqeberha | F31: 45108 | G31: Dormant | H31: =TRUE()
A32: 262797 | B32: Dineo Khumalo | C32: +27473766683 | D32: Northern Cape | E32: Springbok | F32: 45768 | G32: Occasional | H32: =TRUE()
A33: 102041 | B33: Sarah Nkosi | C33: +27472832364 | D33: KwaZulu-Natal | E33: Newcastle | F33: 45161 | G33: Frequent | H33: =TRUE()
A34: 314147 | B34: Lwazi Petersen | C34: +27478714817 | D34: KwaZulu-Natal | E34: Durban | F34: 45539 | G34: Occasional | H34: =TRUE()
A35: 334075 | B35: Zanele Molefe | C35: +27471062156 | D35: Gauteng | E35: Roodepoort | F35: 45486 | G35: Regular | H35: =TRUE()
A36: 209696 | B36: Riaan Dlamini | C36: +27473672456 | D36: Gauteng | E36: Sandton | F36: 45048 | G36: Frequent | H36: =TRUE()
A37: 65478 | B37: Refilwe Mahlangu | C37: +27472070827 | D37: Gauteng | E37: Centurion | F37: 45648 | G37: Occasional | H37: =FALSE()
A38: 88465 | B38: Johan Khumalo | C38: +27477854377 | D38: Limpopo | E38: Mokopane | F38: 44643 | G38: Dormant | H38: =TRUE()
A39: 135261 | B39: Mandla Adams | C39: +27477706434 | D39: KwaZulu-Natal | E39: Richards Bay | F39: 45519 | G39: Occasional | H39: =TRUE()
A40: 175273 | B40: Megan Zulu | C40: +27477656488 | D40: KwaZulu-Natal | E40: Umhlanga | F40: 44594 | G40: Occasional | H40: =TRUE()
A41: 136537 | B41: Sipho Nkosi | C41: +27478279462 | D41: Gauteng | E41: Sandton | F41: 44365 | G41: Dormant | H41: =TRUE()
A42: 177146 | B42: Johan Tshabalala | C42: +27479602965 | D42: KwaZulu-Natal | E42: Umhlanga | F42: 45261 | G42: Dormant | H42: =TRUE()
A43: 154653 | B43: Naledi Petersen | C43: +27479744969 | D43: Eastern Cape | E43: East London | F43: 44237 | G43: Regular | H43: =TRUE()
A44: 42593 | B44: Daniel Daniels | C44: +27476530498 | D44: Mpumalanga | E44: Middelburg | F44: 45645 | G44: Dormant | H44: =TRUE()
A45: 217333 | B45: Pieter Khumalo | C45: +27473512155 | D45: Limpopo | E45: Mokopane | F45: 45784 | G45: Regular | H45: =TRUE()
A46: 298065 | B46: Nomvula Molefe | C46: +27472995586 | D46: KwaZulu-Natal | E46: Umhlanga | F46: 44869 | G46: Occasional | H46: =TRUE()
A47: 297466 | B47: Anika Venter | C47: +27477111466 | D47: Western Cape | E47: Bellville | F47: 46050 | G47: Dormant | H47: =TRUE()
A48: 217463 | B48: Liam Mahlangu | C48: +27478856883 | D48: Gauteng | E48: Sandton | F48: 44557 | G48: Dormant | H48: =FALSE()
A49: 362902 | B49: Megan Steyn | C49: +27472232773 | D49: Mpumalanga | E49: Secunda | F49: 44248 | G49: Occasional | H49: =TRUE()
A50: 62081 | B50: Zanele Adams | C50: +27472681293 | D50: Gauteng | E50: Roodepoort | F50: 44518 | G50: Regular | H50: =FALSE()
A51: 130822 | B51: Daniel Tshabalala | C51: +27474921821 | D51: KwaZulu-Natal | E51: Newcastle | F51: 45282 | G51: Dormant | H51: =TRUE()
A52: 98791 | B52: Naledi Fourie | C52: +27474381793 | D52: KwaZulu-Natal | E52: Newcastle | F52: 44509 | G52: Dormant | H52: =TRUE()
A53: 232722 | B53: Nomvula Sithole | C53: +27476496743 | D53: Mpumalanga | E53: Secunda | F53: 45110 | G53: Occasional | H53: =TRUE()
A54: 83598 | B54: Ayanda Jacobs | C54: +27473581718 | D54: KwaZulu-Natal | E54: Umhlanga | F54: 44790 | G54: Occasional | H54: =TRUE()
A55: 67900 | B55: Megan Mokoena | C55: +27474300324 | D55: Limpopo | E55: Mokopane | F55: 45029 | G55: Occasional | H55: =TRUE()
A56: 391413 | B56: Sipho Pillay | C56: +27472409728 | D56: Gauteng | E56: Johannesburg | F56: 44458 | G56: Occasional | H56: =TRUE()
A57: 297583 | B57: Werner Jacobs | C57: +27479163342 | D57: Gauteng | E57: Midrand | F57: 44449 | G57: Occasional | H57: =TRUE()
A58: 122901 | B58: Kagiso Khumalo | C58: +27477711948 | D58: Limpopo | E58: Polokwane | F58: 44462 | G58: Occasional | H58: =TRUE()
A59: 150380 | B59: Lwazi Smith | C59: +27477063141 | D59: Western Cape | E59: Paarl | F59: 45250 | G59: Regular | H59: =TRUE()
A60: 112345 | B60: Lerato Maluleke | C60: +27473017411 | D60: North West | E60: Potchefstroom | F60: 45283 | G60: Dormant | H60: =TRUE()
A61: 324066 | B61: Kagiso Mthembu | C61: +27478698196 | D61: KwaZulu-Natal | E61: Richards Bay | F61: 45412 | G61: Occasional | H61: =TRUE()
A62: 363209 | B62: Sarah Steyn | C62: +27473138928 | D62: Western Cape | E62: Somerset West | F62: 44760 | G62: Dormant | H62: =TRUE()
A63: 71161 | B63: Anika Sithole | C63: +27474735269 | D63: Gauteng | E63: Midrand | F63: 44455 | G63: Occasional | H63: =FALSE()
A64: 31684 | B64: Johan Adams | C64: +27471402381 | D64: Gauteng | E64: Sandton | F64: 44397 | G64: Occasional | H64: =TRUE()
A65: 76656 | B65: Megan Smith | C65: +27472237099 | D65: KwaZulu-Natal | E65: Umhlanga | F65: 45585 | G65: Regular | H65: =FALSE()
A66: 83649 | B66: Sipho Hendricks | C66: +27473444667 | D66: Western Cape | E66: Somerset West | F66: 44545 | G66: Dormant | H66: =TRUE()
A67: 340672 | B67: Refilwe Adams | C67: +27473182275 | D67: Mpumalanga | E67: Mbombela | F67: 45723 | G67: Dormant | H67: =FALSE()
A68: 170656 | B68: Chloe Smith | C68: +27477504646 | D68: Western Cape | E68: Cape Town | F68: 45896 | G68: Occasional | H68: =TRUE()
A69: 114823 | B69: Zanele van der Merwe | C69: +27476522337 | D69: Gauteng | E69: Sandton | F69: 44848 | G69: Frequent | H69: =TRUE()
A70: 341991 | B70: Jaco Ngcobo | C70: +27473078407 | D70: Eastern Cape | E70: Uitenhage | F70: 44727 | G70: Occasional | H70: =TRUE()
A71: 397537 | B71: Sipho Mahlangu | C71: +27473790202 | D71: Mpumalanga | E71: Secunda | F71: 45049 | G71: Occasional | H71: =TRUE()
A72: 376963 | B72: Megan van der Merwe | C72: +27476557682 | D72: Western Cape | E72: Somerset West | F72: 45785 | G72: Dormant | H72: =TRUE()
A73: 191733 | B73: Tshepo Nkosi | C73: +27471186679 | D73: Eastern Cape | E73: Mthatha | F73: 45995 | G73: Regular | H73: =TRUE()
A74: 277803 | B74: Fatima Sithole | C74: +27471973091 | D74: Limpopo | E74: Thohoyandou | F74: 44547 | G74: Occasional | H74: =FALSE()
A75: 275876 | B75: Khanyi Zulu | C75: +27472505453 | D75: Western Cape | E75: Cape Town | F75: 44273 | G75: Dormant | H75: =FALSE()
A76: 197371 | B76: Riaan Pretorius | C76: +27472109478 | D76: Northern Cape | E76: Springbok | F76: 45312 | G76: Regular | H76: =TRUE()
A77: 344919 | B77: Mandla Daniels | C77: +27473861069 | D77: KwaZulu-Natal | E77: Umhlanga | F77: 44241 | G77: Dormant | H77: =TRUE()
A78: 22833 | B78: Anika Botha | C78: +27471506437 | D78: Eastern Cape | E78: Mthatha | F78: 46110 | G78: Occasional | H78: =TRUE()
A79: 183383 | B79: Thabo Khumalo | C79: +27476682559 | D79: Limpopo | E79: Mokopane | F79: 44816 | G79: Occasional | H79: =TRUE()
A80: 177747 | B80: Liam Molefe | C80: +27471324910 | D80: KwaZulu-Natal | E80: Newcastle | F80: 45532 | G80: Occasional | H80: =TRUE()
A81: 301488 | B81: Precious Fourie | C81: +27472775202 | D81: Eastern Cape | E81: Gqeberha | F81: 44662 | G81: Occasional | H81: =TRUE()
A82: 85422 | B82: Fatima Hendricks | C82: +27479998355 | D82: KwaZulu-Natal | E82: Pinetown | F82: 46131 | G82: Frequent | H82: =FALSE()
A83: 174231 | B83: Ayanda Pretorius | C83: +27476805868 | D83: KwaZulu-Natal | E83: Pinetown | F83: 45173 | G83: Regular | H83: =TRUE()
A84: 347416 | B84: Naledi Dlamini | C84: +27471159876 | D84: Gauteng | E84: Benoni | F84: 45900 | G84: Occasional | H84: =TRUE()
A85: 94293 | B85: Chloe Tshabalala | C85: +27472117768 | D85: Mpumalanga | E85: Mbombela | F85: 46099 | G85: Occasional | H85: =TRUE()
A86: 338272 | B86: Fatima Mokoena | C86: +27479930930 | D86: Eastern Cape | E86: East London | F86: 45845 | G86: Occasional | H86: =TRUE()
A87: 128253 | B87: Sarah Smith | C87: +27474884424 | D87: Eastern Cape | E87: Uitenhage | F87: 46103 | G87: Dormant | H87: =TRUE()
A88: 266382 | B88: Werner Dlamini | C88: +27474991238 | D88: Gauteng | E88: Pretoria | F88: 45138 | G88: Occasional | H88: =TRUE()
A89: 265537 | B89: Daniel Ngcobo | C89: +27473356786 | D89: Eastern Cape | E89: East London | F89: 44921 | G89: Occasional | H89: =TRUE()
A90: 167761 | B90: Lerato Venter | C90: +27475703407 | D90: Western Cape | E90: Somerset West | F90: 45364 | G90: Occasional | H90: =TRUE()
A91: 149203 | B91: Lwazi Sithole | C91: +27471366096 | D91: Gauteng | E91: Soweto | F91: 45838 | G91: Occasional | H91: =TRUE()
A92: 298947 | B92: Liam Steyn | C92: +27474393923 | D92: KwaZulu-Natal | E92: Pietermaritzburg | F92: 45870 | G92: Occasional | H92: =FALSE()
A93: 30943 | B93: Lerato Petersen | C93: +27478266975 | D93: North West | E93: Potchefstroom | F93: 44840 | G93: Dormant | H93: =TRUE()
A94: 7309 | B94: Zanele Petersen | C94: +27478394362 | D94: Western Cape | E94: George | F94: 45153 | G94: Occasional | H94: =TRUE()
A95: 91847 | B95: Aisha Mahlangu | C95: +27475348570 | D95: Limpopo | E95: Thohoyandou | F95: 45866 | G95: Dormant | H95: =TRUE()
A96: 363404 | B96: Thabo Naidoo | C96: +27472206804 | D96: Western Cape | E96: Paarl | F96: 45917 | G96: Regular | H96: =TRUE()
A97: 4865 | B97: Liam Smith | C97: +27475211919 | D97: Limpopo | E97: Mokopane | F97: 44475 | G97: Dormant | H97: =TRUE()
A98: 252765 | B98: Liam Ngcobo | C98: +27471186927 | D98: Free State | E98: Bethlehem | F98: 44231 | G98: Occasional | H98: =TRUE()
A99: 45710 | B99: Mandla Molefe | C99: +27478566422 | D99: KwaZulu-Natal | E99: Pietermaritzburg | F99: 45095 | G99: Occasional | H99: =TRUE()
A100: 81749 | B100: Dineo Maluleke | C100: +27479158624 | D100: Northern Cape | E100: Upington | F100: 45263 | G100: Regular | H100: =TRUE()
A101: 204373 | B101: Zanele Hendricks | C101: +27476151550 | D101: Gauteng | E101: Roodepoort | F101: 45259 | G101: Regular | H101: =TRUE()
A102: 51692 | B102: Kagiso Smith | C102: +27473167531 | D102: Limpopo | E102: Thohoyandou | F102: 44612 | G102: Dormant | H102: =TRUE()
A103: 343175 | B103: Chloe Pillay | C103: +27475074497 | D103: Mpumalanga | E103: Mbombela | F103: 45479 | G103: Dormant | H103: =TRUE()
A104: 66290 | B104: Mandla Petersen | C104: +27472718075 | D104: Gauteng | E104: Benoni | F104: 44258 | G104: Occasional | H104: =TRUE()
... A110: 188684 | B110: Sarah Jacobs | C110: +27479491899 | D110: Gauteng | E110: Benoni | F110: 44782 | G110: Dormant | H110: =TRUE()
A111: 194907 | B111: Emma Daniels | C111: +27471260005 | D111: KwaZulu-Natal | E111: Umhlanga | F111: 45159 | G111: Regular | H111: =FALSE()
A112: 341147 | B112: Thabo Smith | C112: +27477961728 | D112: Eastern Cape | E112: East London | F112: 45442 | G112: Occasional | H112: =TRUE()
A113: 149219 | B113: Mandla Hendricks | C113: +27476470304 | D113: Western Cape | E113: Paarl | F113: 45014 | G113: Occasional | H113: =TRUE()
A114: 331520 | B114: Ayanda Adams | C114: +27478622531 | D114: Gauteng | E114: Roodepoort | F114: 44837 | G114: Dormant | H114: =TRUE()
...

Sheet Couriers
A1: courier_id | B1: courier_name | C1: region | D1: vehicle_type | E1: hired_date
A2: 1 | B2: Jenna Talbot | C2: KwaZulu-Natal | D2: Motorcycle | E2: 43920
A3: 2 | B3: Mr Julian Carroll | C3: Limpopo | D3: 4-Ton Truck | E3: 43448
A4: 3 | B4: Gerard Chamberlain | C4: Gauteng | D4: Motorcycle | E4: 44238
A5: 4 | B5: Alex Hughes-Smith | C5: Gauteng | D5: Motorcycle | E5: 43858
A6: 5 | B6: Leigh Burgess | C6: Gauteng | D6: 4-Ton Truck | E6: 44675
A7: 6 | B7: Mr Phillip Lloyd | C7: Eastern Cape | D7: Panel Van | E7: 43690
A8: 7 | B8: Dr Peter Bevan | C8: North West | D8: 1-Ton Bakkie | E8: 43768
A9: 8 | B9: Mr Julian Browne | C9: Gauteng | D9: Motorcycle | E9: 45652
A10: 9 | B10: Brett Hill | C10: Limpopo | D10: Motorcycle | E10: 45313
A11: 10 | B11: Joel Stephens | C11: Gauteng | D11: Motorcycle | E11: 45261
A12: 11 | B12: Dr Stewart Sharp | C12: KwaZulu-Natal | D12: 1-Ton Bakkie | E12: 43982
A13: 12 | B13: Allan Burke | C13: Eastern Cape | D13: Panel Van | E13: 45643
... A501: 500 | B501: Maurice Graham-Faulkner | C501: Gauteng | D501: Panel Van | E501: 44989
